registry/__init__.py
registry/registry.py
registry/version.py
callable_registry-1.0.1.dist-info/WHEEL
callable_registry-1.0.1.dist-info/METADATA
callable_registry-1.0.1.dist-info/RECORD
