Metadata-Version: 2.1
Name: callable-registry
Version: 1.0.1
License: Apache
Author-email: Scott Chase Waggener <tidalpaladin@protonmail.com>,Tim Cogan <tim@cogan.dev>
Requires-Python: >=3.7
Requires-Dist: typing_extensions; python_version < "3.11"
